pacpush.py
pacpush-3.5.dist-info/METADATA
pacpush-3.5.dist-info/WHEEL
pacpush-3.5.dist-info/entry_points.txt
pacpush-3.5.dist-info/top_level.txt
pacpush-3.5.dist-info/RECORD
