Metadata-Version: 2.4
Name: pacpush
Version: 3.5
Summary: Utility to push an Arch host's package and AUR caches to other hosts
Author-email: Mark Blakeney <mark.blakeney@bullet-systems.net>
License-Expression: GPL-3.0-or-later
Project-URL: Homepage, https://github.com/bulletmark/pacpush
Keywords: pacman,pacserve
Classifier: Programming Language :: Python :: 3
Requires-Python: >=3.8
Requires-Dist: platformdirs
Requires-Dist: argparse-from-file
Requires-Dist: requests
Requires-Dist: pyalpm
